odoo10_addon_privacy_consent-10.0.1.0.0.99.dev25-py3.8-nspkg.pth
odoo/addons/privacy_consent/README.rst
odoo/addons/privacy_consent/__init__.py
odoo/addons/privacy_consent/__manifest__.py
odoo/addons/privacy_consent/controllers/__init__.py
odoo/addons/privacy_consent/controllers/main.py
odoo/addons/privacy_consent/data/ir_actions_server.xml
odoo/addons/privacy_consent/data/ir_cron.xml
odoo/addons/privacy_consent/data/mail.xml
odoo/addons/privacy_consent/i18n/de.po
odoo/addons/privacy_consent/i18n/es.po
odoo/addons/privacy_consent/i18n/fr.po
odoo/addons/privacy_consent/i18n/privacy_consent.pot
odoo/addons/privacy_consent/i18n/pt.po
odoo/addons/privacy_consent/models/__init__.py
odoo/addons/privacy_consent/models/mail_mail.py
odoo/addons/privacy_consent/models/mail_template.py
odoo/addons/privacy_consent/models/privacy_activity.py
odoo/addons/privacy_consent/models/privacy_consent.py
odoo/addons/privacy_consent/models/res_partner.py
odoo/addons/privacy_consent/readme/CONTRIBUTORS.rst
odoo/addons/privacy_consent/readme/DESCRIPTION.rst
odoo/addons/privacy_consent/readme/INSTALL.rst
odoo/addons/privacy_consent/readme/USAGE.rst
odoo/addons/privacy_consent/security/ir.model.access.csv
odoo/addons/privacy_consent/static/description/icon.png
odoo/addons/privacy_consent/static/description/index.html
odoo/addons/privacy_consent/templates/form.xml
odoo/addons/privacy_consent/tests/__init__.py
odoo/addons/privacy_consent/tests/test_consent.py
odoo/addons/privacy_consent/views/privacy_activity.xml
odoo/addons/privacy_consent/views/privacy_consent.xml
odoo/addons/privacy_consent/views/res_partner.xml
odoo10_addon_privacy_consent-10.0.1.0.0.99.dev25.dist-info/METADATA
odoo10_addon_privacy_consent-10.0.1.0.0.99.dev25.dist-info/WHEEL
odoo10_addon_privacy_consent-10.0.1.0.0.99.dev25.dist-info/namespace_packages.txt
odoo10_addon_privacy_consent-10.0.1.0.0.99.dev25.dist-info/top_level.txt
odoo10_addon_privacy_consent-10.0.1.0.0.99.dev25.dist-info/RECORD
