Metadata-Version: 2.1
Name: odoo10-addon-privacy-consent
Version: 10.0.1.0.0.99.dev25
Summary: Allow people to explicitly accept or reject inclusion in some activity, GDPR compliant
Home-page: https://github.com/OCA/management-activity
Author: Tecnativa, Odoo Community Association (OCA)
Author-email: support@odoo-community.org
License: AGPL-3
Platform: UNKNOWN
Classifier: Programming Language :: Python
Classifier: Framework :: Odoo
Classifier: Framework :: Odoo :: 10.0
Classifier: License :: OSI Approved :: GNU Affero General Public License v3
Classifier: Development Status :: 5 - Production/Stable
Requires-Python: ~=2.7
Requires-Dist: odoo10-addon-privacy
Requires-Dist: odoo <10.1dev,>=10.0
